synloc/__init__.py
synloc/clusterResampler.py
synloc/dists.py
synloc/kNNResampler.py
synloc/tools.py
synloc-0.2.4.dist-info/licenses/LICENSE
synloc-0.2.4.dist-info/METADATA
synloc-0.2.4.dist-info/WHEEL
synloc-0.2.4.dist-info/top_level.txt
synloc-0.2.4.dist-info/RECORD
