Metadata-Version: 2.4
Name: synloc
Version: 0.2.4
Summary: A Python package to create synthetic data from locally estimated distributions
Home-page: https://github.com/alfurka/synloc
Author: Ali Furkan Kalay
Author-email: Ali Furkan Kalay <alfurka@gmail.com>
License: MIT
Project-URL: Homepage, https://github.com/alfurka/synloc
Project-URL: Documentation, https://alfurka.github.io/synloc/
Keywords: copulas,distributions,sampling,synthetic-data,oversampling,nonparametric-distributions,semiparametric,nonparametric,knn,clustering,k-means,multivariate-distributions
Classifier: Development Status :: 2 - Pre-Alpha
Classifier: Programming Language :: Python :: 3
Classifier: Intended Audience :: Science/Research
Classifier: Operating System :: OS Independent
Requires-Python: >=3.8
License-File: LICENSE
Requires-Dist: pandas
Requires-Dist: numpy
Requires-Dist: scipy
Requires-Dist: matplotlib
Requires-Dist: scikit-learn
Requires-Dist: tqdm
Dynamic: author
Dynamic: home-page
Dynamic: license-file
Dynamic: requires-python
